{
    "ravines": false,
    "dimensionalComposite": [
        {
            "dimension": "floor",
            "primary": true,
            "weight": 1
        },
        {
            "dimension": "center",
            "weight": 2
        },
        {
            "dimension": "ceiling",
            "inverted": true,
            "weight": 1
        }
    ],
    "environment": "NETHER",
    "fluidPalette": {
        "palette": [
            {
                "block": "lava"
            }
        ]
    },
    "rockPalette": {
        "palette": [
            {
                "block": "netherrack"
            }
        ]
    },
    "name": "Nether",
    "version": 1
}
